CHANGELOG
MANIFEST.in
README.md
setup.cfg
setup.py
context_io_2.egg-info/PKG-INFO
context_io_2.egg-info/SOURCES.txt
context_io_2.egg-info/dependency_links.txt
context_io_2.egg-info/not-zip-safe
context_io_2.egg-info/requires.txt
context_io_2.egg-info/top_level.txt
contextio/__init__.py
contextio/util.py