Metadata-Version: 1.0
Name: context-io-2
Version: 2.0.1
Summary: I did not create this package; I'm just adding it to pypi.  It's already freely available on GitHub.
Home-page: http://context.io
Author: Tony Blank, Jesse Dhillon
Author-email: tony@context.io, jesse@deva0.net
License: UNKNOWN
Keywords: contextIO,dokdok,imap,oauth
Platform: UNKNOWN
